{ "eventVersion": "1.05", "userIdentity": { "type": "AssumedRole", "principalId": "AROAJHKNNBGSIEZ35WOQA:e4ace9c4353d4184be80614fbd2b2110", "arn": "arn:aws:sts::061305161530:assumed-role/rig-task-rig_controller_api-unstable-d587233/e4ace9c4353d4184be80614fbd2b2110", "accountId": "061305161530", "accessKeyId": "ASIAQ4RQSQ45LUQADAK3", "sessionContext": { "attributes": { "mfaAuthenticated": "false", "creationDate": "2019-03-27T14:02:10Z" }, "sessionIssuer": { "type": "Role", "principalId": "AROAJHKNNBGSIEZ35WOQA", "arn": "arn:aws:iam::061305161530:role/rig-task-rig_controller_api-unstable-d587233", "accountId": "061305161530", "userName": "rig-task-rig_controller_api-unstable-d587233" } } }, "eventTime": "2019-03-27T14:55:18Z", "eventSource": "secretsmanager.amazonaws.com", "eventName": "GetSecretValue", "awsRegion": "us-east-1", "sourceIPAddress": "34.232.53.253", "userAgent": "Boto3/1.9.97 Python/3.7.2 Linux/4.14.94-89.73.amzn2.x86_64 exec-env/AWS_ECS_FARGATE Botocore/1.12.97", "requestParameters": { "secretId": "unstable/rig_controller_api/JWT_signing_key", "versionStage": "AWSPREVIOUS" }, "responseElements": null, "requestID": "b4bc129e-d8a7-4250-b25d-4d0d237490dd", "eventID": "bdbd648a-51b5-458e-9b79-d37449a7050b", "eventType": "AwsApiCall", "recipientAccountId": "061305161530" }

{ "eventVersion": "1.05", "userIdentity": { "type": "AssumedRole", "principalId": "AROAJHKNNBGSIEZ35WOQA:e4ace9c4353d4184be80614fbd2b2110", "arn": "arn:aws:sts::061305161530:assumed-role/rig-task-rig_controller_api-unstable-d587233/e4ace9c4353d4184be80614fbd2b2110", "accountId": "061305161530", "accessKeyId": "ASIAJFGR5LRWP6BBWD5Q", "sessionContext": { "attributes": { "mfaAuthenticated": "false", "creationDate": "2019-03-27T14:02:10Z" }, "sessionIssuer": { "type": "Role", "principalId": "AROAJHKNNBGSIEZ35WOQA", "arn": "arn:aws:iam::061305161530:role/rig-task-rig_controller_api-unstable-d587233", "accountId": "061305161530", "userName": "rig-task-rig_controller_api-unstable-d587233" } }, "invokedBy": "secretsmanager.amazonaws.com" }, "eventTime": "2019-03-27T14:55:11Z", "eventSource": "kms.amazonaws.com", "eventName": "Decrypt", "awsRegion": "us-east-1", "sourceIPAddress": "secretsmanager.amazonaws.com", "userAgent": "secretsmanager.amazonaws.com", "requestParameters": { "encryptionContext": { "SecretARN": "arn:aws:secretsmanager:us-east-1:061305161530:secret:unstable/rig_controller_api/JWT_signing_key-xfgtFB", "SecretVersionId": "d26be305-8cfc-4b0d-8e60-a6b48bfb76c0" } }, "responseElements": null, "requestID": "346ad9d9-13d9-4c63-9c53-1e91f261bfed", "eventID": "481bfb37-d55b-479d-b70a-d58195af4969", "readOnly": true, "resources": [ { "ARN": "arn:aws:kms:us-east-1:061305161530:key/c2b127e2-2265-44c0-9d30-3a4ab91de20a", "accountId": "061305161530", "type": "AWS::KMS::Key" } ], "eventType": "AwsApiCall", "recipientAccountId": "061305161530", "vpcEndpointId": "vpce-0b078abfcbe4622a3" }

{ "eventVersion": "1.05", "userIdentity": { "type": "AssumedRole", "principalId": "AROAJD7M6BBLUA5FSXP6Q:rowan.cota", "arn": "arn:aws:sts::061305161530:assumed-role/admin/rowan.cota", "accountId": "061305161530", "accessKeyId": "ASIAQ4RQSQ45PTKNTI3D", "sessionContext": { "attributes": { "mfaAuthenticated": "true", "creationDate": "2019-03-27T18:39:05Z" }, "sessionIssuer": { "type": "Role", "principalId": "AROAJD7M6BBLUA5FSXP6Q", "arn": "arn:aws:iam::061305161530:role/admin", "accountId": "061305161530", "userName": "admin" } } }, "eventTime": "2019-03-27T19:00:38Z", "eventSource": "secretsmanager.amazonaws.com", "eventName": "GetSecretValue", "awsRegion": "us-east-1", "sourceIPAddress": "65.254.2.50", "userAgent": "aws-internal/3 aws-sdk-java/1.11.479 Linux/4.9.137-0.1.ac.218.74.329.metal1.x86_64 OpenJDK_64-Bit_Server_VM/25.192-b12 java/1.8.0_192", "requestParameters": { "secretId": "unstable/rig_controller_api/JWT_signing_key" }, "responseElements": null, "requestID": "be111de1-91f7-4977-abe9-908ef87c75da", "eventID": "1305fd14-18cd-4b0f-a137-8c3ee53ec6aa", "eventType": "AwsApiCall", "recipientAccountId": "061305161530" }